[
  {
    "inquiry_id": "INQ-20260123-001",
    "case_id": "case_010",
    "case_type": "consumer",
    "full_name": "Utsav Mehta",
    "phone_number": "+91 8306 08059",
    "email": "abc@xyz.com",
    "city": "Rajkot",
    "state": "Gujarat",
    "case_description": "I was very sad and I did this",
    "requirements": "I want Help with the lawyer",
    "expectations": "I want to win the case or get a bail",
    "urgency": "urgent",
    "preferred_date": "2026-01-30",
    "previous_lawyer": "no",
    "budget_range": "2l-5l",
    "additional_notes": "I am okay with 10%+/-",
    "submitted_at": "2026-01-23T09:44:57.886Z",
    "status": "reviewed",
    "created_at": "2026-01-23T15:14:58.221544",
    "updated_at": "2026-01-23T15:29:17.978174"
  },
  {
    "inquiry_id": "INQ-20260123-003",
    "case_id": "case_010",
    "case_type": "intellectual",
    "full_name": "Utsav Mehta",
    "phone_number": "+91 99257 16941",
    "email": null,
    "city": "Mumbai",
    "state": "Nagaland",
    "case_description": "Okay easy easy",
    "requirements": "Nothing just testing",
    "expectations": "I want a free consultancy",
    "urgency": "low",
    "preferred_date": "2026-02-01",
    "previous_lawyer": "yes",
    "budget_range": "under-10k",
    "additional_notes": null,
    "submitted_at": "2026-01-23T09:57:40.803Z",
    "status": "closed",
    "created_at": "2026-01-23T15:27:41.134230",
    "updated_at": "2026-01-23T15:29:10.483750"
  },
  {
    "inquiry_id": "INQ-20260123-003",
    "case_id": null,
    "case_type": "criminal",
    "full_name": "Mehta",
    "phone_number": "+91 99999 99999",
    "email": null,
    "city": "MMMMsd",
    "state": "Mizoram",
    "case_description": "okay okay okay test",
    "requirements": "Nothing just testinhg",
    "expectations": "Free free free",
    "urgency": "high",
    "preferred_date": null,
    "previous_lawyer": "no",
    "budget_range": "flexible",
    "additional_notes": null,
    "submitted_at": "2026-01-23T10:01:10.964Z",
    "status": "pending",
    "created_at": "2026-01-23T15:31:11.291926"
  },
  {
    "inquiry_id": "INQ-20260123-004",
    "case_id": "case_003",
    "case_type": "intellectual",
    "full_name": "YYYYY yp",
    "phone_number": "+91 99257 16941",
    "email": null,
    "city": "xyxz",
    "state": "Gujarat",
    "case_description": "okay okay oak",
    "requirements": "silver oak",
    "expectations": "nothing nothing",
    "urgency": "low",
    "preferred_date": null,
    "previous_lawyer": "no",
    "budget_range": "above-5l",
    "additional_notes": null,
    "submitted_at": "2026-01-23T15:37:50.249795",
    "status": "pending",
    "created_at": "2026-01-23T15:37:50.249795"
  },
  {
    "inquiry_id": "INQ-20260123-005",
    "case_id": "case_003",
    "case_type": "intellectual",
    "full_name": "Mehta",
    "phone_number": "+91 83060 80595",
    "email": "abc@gmail.com",
    "city": "Mumbai",
    "state": "Maharashtra",
    "case_description": "I want a free visit.",
    "requirements": "I want a free visit.",
    "expectations": "I want a free visit.",
    "urgency": "high",
    "preferred_date": null,
    "previous_lawyer": "no",
    "budget_range": "25k-50k",
    "additional_notes": null,
    "submitted_at": "2026-01-23T15:48:27.203454",
    "status": "pending",
    "created_at": "2026-01-23T15:48:27.203454"
  },
  {
    "inquiry_id": "INQ-20260123-006",
    "case_id": "case_008",
    "case_type": "consumer",
    "full_name": "uishash n m",
    "phone_number": "+91 88888 88888",
    "email": null,
    "city": "utsav",
    "state": "Manipur",
    "case_description": "jhasjn kjans jns ka ska sk kj ask k",
    "requirements": "kasjk skj ksjaks ka sk m",
    "expectations": "asjaks km akjs kaj ska sk aks k",
    "urgency": "urgent",
    "preferred_date": null,
    "previous_lawyer": "no",
    "budget_range": "flexible",
    "additional_notes": null,
    "submitted_at": "2026-01-23T18:08:37.280345",
    "status": "pending",
    "created_at": "2026-01-23T18:08:37.280345"
  },
  {
    "inquiry_id": "INQ-20260123-007",
    "case_id": "case_014",
    "case_type": "corporate",
    "full_name": "jhsdjsahs",
    "phone_number": "+91 54654 65465",
    "email": null,
    "city": "Yuybduahb uaybsuh l",
    "state": "Maharashtra",
    "case_description": "inijnija sij iajsija isja isj iaj sj ksj ak j",
    "requirements": "yyiabsihbaihsbuha suyaysbua syau suauys ua su us",
    "expectations": "nononoonoon ono no no no no oo",
    "urgency": "high",
    "preferred_date": null,
    "previous_lawyer": "no",
    "budget_range": "50k-1l",
    "additional_notes": null,
    "submitted_at": "2026-01-23T18:09:51.314516",
    "status": "pending",
    "created_at": "2026-01-23T18:09:51.314516"
  },
  {
    "inquiry_id": "INQ-20260207-001",
    "case_id": "case_001",
    "case_type": "criminal",
    "full_name": "Nilesh Nikam",
    "phone_number": "+91 90390 31115",
    "email": "nileshnikam2223@gmail.com",
    "city": "ahmednagar",
    "state": "Maharashtra",
    "case_description": "case is related to criminal offence",
    "requirements": "consultation",
    "expectations": "result is on my side",
    "urgency": "medium",
    "preferred_date": "2026-02-12",
    "previous_lawyer": "no",
    "budget_range": "50k-1l",
    "additional_notes": null,
    "submitted_at": "2026-02-07T11:04:08.517943",
    "status": "contacted",
    "created_at": "2026-02-07T11:04:08.517943",
    "updated_at": "2026-02-07T11:28:28.242590"
  }
]